[
  {
    "id": 17582310345,
    "date": "2026-03-02",
    "totalMeters": 1125,
    "movingSeconds": 2934,
    "pace100m": 260.8,
    "paceFormatted": "4:21"
  },
  {
    "id": 17555952154,
    "date": "2026-02-28",
    "totalMeters": 350,
    "movingSeconds": 866,
    "pace100m": 247.42857142857142,
    "paceFormatted": "4:07"
  },
  {
    "id": 17535565885,
    "date": "2026-02-26",
    "totalMeters": 1200,
    "movingSeconds": 3400,
    "pace100m": 283.33333333333337,
    "paceFormatted": "4:43"
  },
  {
    "id": 17499551240,
    "date": "2026-02-23",
    "totalMeters": 1925,
    "movingSeconds": 4036,
    "pace100m": 209.66233766233765,
    "paceFormatted": "3:30"
  }
]