[
  {
    "date": "2025-01-07",
    "corsa": 0,
    "nuoto": 1.57,
    "ciclismo": 0,
    "camminata": 0
  },
  {
    "date": "2025-01-09",
    "corsa": 0,
    "nuoto": 2.05,
    "ciclismo": 0,
    "camminata": 0
  },
  {
    "date": "2025-01-13",
    "corsa": 0,
    "nuoto": 1.93,
    "ciclismo": 0,
    "camminata": 0
  },
  {
    "date": "2025-01-16",
    "corsa": 0,
    "nuoto": 1.32,
    "ciclismo": 0,
    "camminata": 0
  },
  {
    "date": "2025-01-20",
    "corsa": 0,
    "nuoto": 1.9,
    "ciclismo": 0,
    "camminata": 0
  },
  {
    "date": "2025-01-22",
    "corsa": 0,
    "nuoto": 0.78,
    "ciclismo": 0,
    "camminata": 0
  },
  {
    "date": "2025-01-23",
    "corsa": 0,
    "nuoto": 0.72,
    "ciclismo": 0,
    "camminata": 0
  },
  {
    "date": "2025-02-03",
    "corsa": 0,
    "nuoto": 1.3,
    "ciclismo": 0,
    "camminata": 0
  },
  {
    "date": "2025-02-06",
    "corsa": 0,
    "nuoto": 1.8,
    "ciclismo": 0,
    "camminata": 0
  },
  {
    "date": "2025-02-07",
    "corsa": 0,
    "nuoto": 2.23,
    "ciclismo": 0,
    "camminata": 0
  },
  {
    "date": "2025-02-10",
    "corsa": 0,
    "nuoto": 1.65,
    "ciclismo": 0,
    "camminata": 0
  },
  {
    "date": "2025-02-11",
    "corsa": 0,
    "nuoto": 1.88,
    "ciclismo": 0,
    "camminata": 0
  },
  {
    "date": "2025-02-13",
    "corsa": 0,
    "nuoto": 1.93,
    "ciclismo": 0,
    "camminata": 0
  },
  {
    "date": "2025-02-17",
    "corsa": 0,
    "nuoto": 2.2,
    "ciclismo": 0,
    "camminata": 0
  },
  {
    "date": "2025-02-19",
    "corsa": 0,
    "nuoto": 1.82,
    "ciclismo": 0,
    "camminata": 0
  },
  {
    "date": "2025-03-09",
    "corsa": 0,
    "nuoto": 0,
    "ciclismo": 34.61,
    "camminata": 0
  },
  {
    "date": "2025-03-18",
    "corsa": 0,
    "nuoto": 2.33,
    "ciclismo": 0,
    "camminata": 0
  },
  {
    "date": "2025-03-21",
    "corsa": 0,
    "nuoto": 0.97,
    "ciclismo": 0,
    "camminata": 0
  },
  {
    "date": "2025-03-24",
    "corsa": 0,
    "nuoto": 2.3,
    "ciclismo": 0,
    "camminata": 0
  },
  {
    "date": "2025-03-25",
    "corsa": 0,
    "nuoto": 0.93,
    "ciclismo": 0,
    "camminata": 0
  },
  {
    "date": "2025-03-26",
    "corsa": 0,
    "nuoto": 0,
    "ciclismo": 0,
    "camminata": 0
  },
  {
    "date": "2025-03-27",
    "corsa": 0,
    "nuoto": 1.52,
    "ciclismo": 0,
    "camminata": 0
  },
  {
    "date": "2025-03-28",
    "corsa": 0,
    "nuoto": 2,
    "ciclismo": 0,
    "camminata": 0
  },
  {
    "date": "2025-03-30",
    "corsa": 0,
    "nuoto": 0,
    "ciclismo": 0,
    "camminata": 0
  },
  {
    "date": "2025-03-31",
    "corsa": 0,
    "nuoto": 1.15,
    "ciclismo": 0,
    "camminata": 0
  },
  {
    "date": "2025-04-01",
    "corsa": 0,
    "nuoto": 2.8,
    "ciclismo": 0,
    "camminata": 0
  },
  {
    "date": "2025-04-03",
    "corsa": 10.19,
    "nuoto": 0,
    "ciclismo": 0,
    "camminata": 0
  },
  {
    "date": "2025-04-04",
    "corsa": 0,
    "nuoto": 2.1,
    "ciclismo": 0,
    "camminata": 0
  },
  {
    "date": "2025-04-06",
    "corsa": 0,
    "nuoto": 0,
    "ciclismo": 0,
    "camminata": 0
  },
  {
    "date": "2025-04-07",
    "corsa": 0,
    "nuoto": 1.88,
    "ciclismo": 0,
    "camminata": 0
  },
  {
    "date": "2025-04-08",
    "corsa": 0,
    "nuoto": 2.15,
    "ciclismo": 0,
    "camminata": 0
  },
  {
    "date": "2025-04-09",
    "corsa": 0,
    "nuoto": 0,
    "ciclismo": 0,
    "camminata": 0
  },
  {
    "date": "2025-04-10",
    "corsa": 0,
    "nuoto": 2.1,
    "ciclismo": 0,
    "camminata": 0
  },
  {
    "date": "2025-04-11",
    "corsa": 0,
    "nuoto": 1.5,
    "ciclismo": 0,
    "camminata": 0
  },
  {
    "date": "2025-04-12",
    "corsa": 0,
    "nuoto": 0,
    "ciclismo": 0,
    "camminata": 4.64
  },
  {
    "date": "2025-04-14",
    "corsa": 6.69,
    "nuoto": 0,
    "ciclismo": 0,
    "camminata": 0
  },
  {
    "date": "2025-04-15",
    "corsa": 0,
    "nuoto": 2.33,
    "ciclismo": 0,
    "camminata": 0
  },
  {
    "date": "2025-04-16",
    "corsa": 6.4,
    "nuoto": 0,
    "ciclismo": 0,
    "camminata": 0
  },
  {
    "date": "2025-04-17",
    "corsa": 0,
    "nuoto": 2.02,
    "ciclismo": 0,
    "camminata": 0
  },
  {
    "date": "2025-04-18",
    "corsa": 17.07,
    "nuoto": 0,
    "ciclismo": 0,
    "camminata": 0
  },
  {
    "date": "2025-04-19",
    "corsa": 0,
    "nuoto": 0,
    "ciclismo": 0,
    "camminata": 0
  },
  {
    "date": "2025-04-21",
    "corsa": 5.48,
    "nuoto": 0,
    "ciclismo": 0,
    "camminata": 0
  },
  {
    "date": "2025-04-22",
    "corsa": 0,
    "nuoto": 2.4,
    "ciclismo": 0,
    "camminata": 0
  },
  {
    "date": "2025-04-24",
    "corsa": 0,
    "nuoto": 0,
    "ciclismo": 0,
    "camminata": 2.62
  },
  {
    "date": "2025-04-25",
    "corsa": 12.19,
    "nuoto": 0,
    "ciclismo": 0,
    "camminata": 0
  },
  {
    "date": "2025-04-26",
    "corsa": 0,
    "nuoto": 0,
    "ciclismo": 0,
    "camminata": 3.85
  },
  {
    "date": "2025-04-27",
    "corsa": 0,
    "nuoto": 0,
    "ciclismo": 0,
    "camminata": 2.56
  },
  {
    "date": "2025-04-28",
    "corsa": 0,
    "nuoto": 2.52,
    "ciclismo": 0,
    "camminata": 0
  },
  {
    "date": "2025-04-29",
    "corsa": 4.72,
    "nuoto": 2.42,
    "ciclismo": 0,
    "camminata": 0
  },
  {
    "date": "2025-05-01",
    "corsa": 0,
    "nuoto": 0,
    "ciclismo": 34.91,
    "camminata": 0
  },
  {
    "date": "2025-05-02",
    "corsa": 0,
    "nuoto": 1.7,
    "ciclismo": 0,
    "camminata": 0
  },
  {
    "date": "2025-05-05",
    "corsa": 0,
    "nuoto": 1.8,
    "ciclismo": 0,
    "camminata": 0
  },
  {
    "date": "2025-05-06",
    "corsa": 10.38,
    "nuoto": 2.02,
    "ciclismo": 0,
    "camminata": 0
  },
  {
    "date": "2025-05-07",
    "corsa": 0,
    "nuoto": 0,
    "ciclismo": 0,
    "camminata": 0.98
  },
  {
    "date": "2025-05-08",
    "corsa": 0,
    "nuoto": 1.3,
    "ciclismo": 0,
    "camminata": 0
  },
  {
    "date": "2025-05-09",
    "corsa": 0,
    "nuoto": 2,
    "ciclismo": 0,
    "camminata": 0
  },
  {
    "date": "2025-05-10",
    "corsa": 0,
    "nuoto": 0,
    "ciclismo": 0,
    "camminata": 4.24
  },
  {
    "date": "2025-05-12",
    "corsa": 8.87,
    "nuoto": 0,
    "ciclismo": 0,
    "camminata": 0
  },
  {
    "date": "2025-05-13",
    "corsa": 0,
    "nuoto": 2.7,
    "ciclismo": 0,
    "camminata": 0
  },
  {
    "date": "2025-05-14",
    "corsa": 0,
    "nuoto": 0,
    "ciclismo": 0,
    "camminata": 2.33
  },
  {
    "date": "2025-05-15",
    "corsa": 0,
    "nuoto": 1.43,
    "ciclismo": 0,
    "camminata": 0
  },
  {
    "date": "2025-05-16",
    "corsa": 8.1,
    "nuoto": 1.9,
    "ciclismo": 0,
    "camminata": 0
  },
  {
    "date": "2025-05-17",
    "corsa": 8.42,
    "nuoto": 0,
    "ciclismo": 0,
    "camminata": 0
  },
  {
    "date": "2025-05-19",
    "corsa": 0,
    "nuoto": 2.33,
    "ciclismo": 0,
    "camminata": 0
  },
  {
    "date": "2025-05-20",
    "corsa": 0,
    "nuoto": 1.8,
    "ciclismo": 0,
    "camminata": 0
  },
  {
    "date": "2025-05-21",
    "corsa": 0,
    "nuoto": 0,
    "ciclismo": 0,
    "camminata": 0
  },
  {
    "date": "2025-05-22",
    "corsa": 5.11,
    "nuoto": 0,
    "ciclismo": 0,
    "camminata": 0
  },
  {
    "date": "2025-05-23",
    "corsa": 0,
    "nuoto": 1.57,
    "ciclismo": 0,
    "camminata": 0
  },
  {
    "date": "2025-05-24",
    "corsa": 0,
    "nuoto": 0,
    "ciclismo": 0,
    "camminata": 4.6
  },
  {
    "date": "2025-05-25",
    "corsa": 12.82,
    "nuoto": 0,
    "ciclismo": 0,
    "camminata": 0
  },
  {
    "date": "2025-05-26",
    "corsa": 0,
    "nuoto": 1.45,
    "ciclismo": 0,
    "camminata": 0
  },
  {
    "date": "2025-05-27",
    "corsa": 0,
    "nuoto": 1.85,
    "ciclismo": 0,
    "camminata": 0
  },
  {
    "date": "2025-05-28",
    "corsa": 0,
    "nuoto": 0,
    "ciclismo": 0,
    "camminata": 9.67
  },
  {
    "date": "2025-05-29",
    "corsa": 0,
    "nuoto": 1.43,
    "ciclismo": 0,
    "camminata": 0
  },
  {
    "date": "2025-06-02",
    "corsa": 5.07,
    "nuoto": 0,
    "ciclismo": 0,
    "camminata": 0
  },
  {
    "date": "2025-06-03",
    "corsa": 0,
    "nuoto": 1.85,
    "ciclismo": 0,
    "camminata": 0
  },
  {
    "date": "2025-06-04",
    "corsa": 0,
    "nuoto": 0,
    "ciclismo": 0,
    "camminata": 4.8
  },
  {
    "date": "2025-06-05",
    "corsa": 0,
    "nuoto": 1.45,
    "ciclismo": 0,
    "camminata": 0
  },
  {
    "date": "2025-06-06",
    "corsa": 0,
    "nuoto": 1.65,
    "ciclismo": 0,
    "camminata": 0
  },
  {
    "date": "2025-06-07",
    "corsa": 0,
    "nuoto": 0,
    "ciclismo": 0,
    "camminata": 4.66
  },
  {
    "date": "2025-06-08",
    "corsa": 0,
    "nuoto": 0.8,
    "ciclismo": 0,
    "camminata": 0
  },
  {
    "date": "2025-06-09",
    "corsa": 5.49,
    "nuoto": 1.8,
    "ciclismo": 0,
    "camminata": 0
  },
  {
    "date": "2025-06-10",
    "corsa": 0,
    "nuoto": 1.7,
    "ciclismo": 0,
    "camminata": 0
  },
  {
    "date": "2025-06-11",
    "corsa": 0,
    "nuoto": 0,
    "ciclismo": 0,
    "camminata": 3.93
  },
  {
    "date": "2025-06-12",
    "corsa": 0,
    "nuoto": 2.55,
    "ciclismo": 0,
    "camminata": 0
  },
  {
    "date": "2025-06-13",
    "corsa": 0,
    "nuoto": 2.75,
    "ciclismo": 0,
    "camminata": 0
  },
  {
    "date": "2025-06-16",
    "corsa": 20.36,
    "nuoto": 0,
    "ciclismo": 0,
    "camminata": 0
  },
  {
    "date": "2025-06-17",
    "corsa": 0,
    "nuoto": 1,
    "ciclismo": 0,
    "camminata": 0
  },
  {
    "date": "2025-06-18",
    "corsa": 0,
    "nuoto": 0,
    "ciclismo": 0,
    "camminata": 2
  },
  {
    "date": "2025-06-19",
    "corsa": 0,
    "nuoto": 1.8,
    "ciclismo": 0,
    "camminata": 0
  },
  {
    "date": "2025-06-20",
    "corsa": 0,
    "nuoto": 1.45,
    "ciclismo": 0,
    "camminata": 0
  },
  {
    "date": "2025-06-21",
    "corsa": 0,
    "nuoto": 0.95,
    "ciclismo": 0,
    "camminata": 0
  },
  {
    "date": "2025-06-23",
    "corsa": 0,
    "nuoto": 1.2,
    "ciclismo": 0,
    "camminata": 0
  },
  {
    "date": "2025-06-25",
    "corsa": 0,
    "nuoto": 1.25,
    "ciclismo": 0,
    "camminata": 0
  },
  {
    "date": "2025-06-27",
    "corsa": 0,
    "nuoto": 0,
    "ciclismo": 0,
    "camminata": 0.93
  },
  {
    "date": "2025-06-28",
    "corsa": 0,
    "nuoto": 0,
    "ciclismo": 0,
    "camminata": 0.78
  },
  {
    "date": "2025-06-30",
    "corsa": 0,
    "nuoto": 2.05,
    "ciclismo": 0,
    "camminata": 0
  },
  {
    "date": "2025-07-01",
    "corsa": 0,
    "nuoto": 2,
    "ciclismo": 0,
    "camminata": 0
  },
  {
    "date": "2025-07-02",
    "corsa": 5.96,
    "nuoto": 0,
    "ciclismo": 0,
    "camminata": 0
  },
  {
    "date": "2025-07-03",
    "corsa": 0,
    "nuoto": 1.82,
    "ciclismo": 0,
    "camminata": 0
  },
  {
    "date": "2025-07-04",
    "corsa": 0,
    "nuoto": 2.3,
    "ciclismo": 0,
    "camminata": 0
  },
  {
    "date": "2025-07-05",
    "corsa": 9.58,
    "nuoto": 0,
    "ciclismo": 0,
    "camminata": 0
  },
  {
    "date": "2025-07-08",
    "corsa": 0,
    "nuoto": 1.98,
    "ciclismo": 0,
    "camminata": 0
  },
  {
    "date": "2025-07-09",
    "corsa": 0,
    "nuoto": 0,
    "ciclismo": 0,
    "camminata": 0
  },
  {
    "date": "2025-07-10",
    "corsa": 0,
    "nuoto": 1.05,
    "ciclismo": 0,
    "camminata": 0
  },
  {
    "date": "2025-07-11",
    "corsa": 0,
    "nuoto": 2.33,
    "ciclismo": 0,
    "camminata": 0
  },
  {
    "date": "2025-07-12",
    "corsa": 8.46,
    "nuoto": 0,
    "ciclismo": 0,
    "camminata": 0
  },
  {
    "date": "2025-07-14",
    "corsa": 0,
    "nuoto": 1.25,
    "ciclismo": 0,
    "camminata": 0
  },
  {
    "date": "2025-07-15",
    "corsa": 0,
    "nuoto": 1.85,
    "ciclismo": 0,
    "camminata": 0
  },
  {
    "date": "2025-07-16",
    "corsa": 0,
    "nuoto": 0,
    "ciclismo": 0,
    "camminata": 0
  },
  {
    "date": "2025-07-17",
    "corsa": 0,
    "nuoto": 0,
    "ciclismo": 0,
    "camminata": 0.55
  },
  {
    "date": "2025-07-18",
    "corsa": 0,
    "nuoto": 1.8,
    "ciclismo": 0,
    "camminata": 0
  },
  {
    "date": "2025-07-19",
    "corsa": 5.7,
    "nuoto": 0,
    "ciclismo": 0,
    "camminata": 0
  },
  {
    "date": "2025-07-20",
    "corsa": 0,
    "nuoto": 1,
    "ciclismo": 0,
    "camminata": 0
  },
  {
    "date": "2025-07-21",
    "corsa": 0,
    "nuoto": 1.35,
    "ciclismo": 0,
    "camminata": 0
  },
  {
    "date": "2025-07-22",
    "corsa": 0,
    "nuoto": 1.8,
    "ciclismo": 0,
    "camminata": 0
  },
  {
    "date": "2025-07-24",
    "corsa": 1.1,
    "nuoto": 0,
    "ciclismo": 0,
    "camminata": 0
  },
  {
    "date": "2025-07-26",
    "corsa": 6,
    "nuoto": 0,
    "ciclismo": 0,
    "camminata": 0
  },
  {
    "date": "2025-08-01",
    "corsa": 0,
    "nuoto": 0,
    "ciclismo": 0,
    "camminata": 1.44
  },
  {
    "date": "2025-08-03",
    "corsa": 0,
    "nuoto": 0,
    "ciclismo": 0,
    "camminata": 0
  },
  {
    "date": "2025-08-04",
    "corsa": 0,
    "nuoto": 1.95,
    "ciclismo": 0,
    "camminata": 0
  },
  {
    "date": "2025-08-05",
    "corsa": 0,
    "nuoto": 1.15,
    "ciclismo": 0,
    "camminata": 0
  },
  {
    "date": "2025-08-06",
    "corsa": 10.06,
    "nuoto": 0,
    "ciclismo": 0,
    "camminata": 0
  },
  {
    "date": "2025-08-08",
    "corsa": 0,
    "nuoto": 0,
    "ciclismo": 35.77,
    "camminata": 0
  },
  {
    "date": "2025-08-11",
    "corsa": 0,
    "nuoto": 2.25,
    "ciclismo": 0,
    "camminata": 0
  },
  {
    "date": "2025-08-13",
    "corsa": 10.08,
    "nuoto": 0,
    "ciclismo": 0,
    "camminata": 0
  },
  {
    "date": "2025-08-16",
    "corsa": 9.55,
    "nuoto": 0,
    "ciclismo": 0,
    "camminata": 0
  },
  {
    "date": "2025-08-17",
    "corsa": 0,
    "nuoto": 0,
    "ciclismo": 0,
    "camminata": 0.6
  },
  {
    "date": "2025-08-18",
    "corsa": 0,
    "nuoto": 0,
    "ciclismo": 0,
    "camminata": 0
  },
  {
    "date": "2025-08-20",
    "corsa": 0,
    "nuoto": 0,
    "ciclismo": 0,
    "camminata": 1.85
  },
  {
    "date": "2025-08-22",
    "corsa": 0,
    "nuoto": 0,
    "ciclismo": 0,
    "camminata": 1.23
  },
  {
    "date": "2025-08-25",
    "corsa": 0,
    "nuoto": 1.25,
    "ciclismo": 0,
    "camminata": 0
  },
  {
    "date": "2025-08-26",
    "corsa": 12.64,
    "nuoto": 1.9,
    "ciclismo": 0,
    "camminata": 0
  },
  {
    "date": "2025-08-30",
    "corsa": 0,
    "nuoto": 0,
    "ciclismo": 0,
    "camminata": 0
  },
  {
    "date": "2025-08-31",
    "corsa": 5.13,
    "nuoto": 0,
    "ciclismo": 0,
    "camminata": 0
  },
  {
    "date": "2025-09-01",
    "corsa": 0,
    "nuoto": 2.02,
    "ciclismo": 0,
    "camminata": 0
  },
  {
    "date": "2025-09-02",
    "corsa": 0,
    "nuoto": 2.02,
    "ciclismo": 0,
    "camminata": 0
  },
  {
    "date": "2025-09-03",
    "corsa": 8.71,
    "nuoto": 0,
    "ciclismo": 0,
    "camminata": 0
  },
  {
    "date": "2025-09-04",
    "corsa": 0,
    "nuoto": 2.02,
    "ciclismo": 0,
    "camminata": 0
  },
  {
    "date": "2025-09-05",
    "corsa": 0,
    "nuoto": 2.02,
    "ciclismo": 0,
    "camminata": 0
  },
  {
    "date": "2025-09-06",
    "corsa": 0,
    "nuoto": 0,
    "ciclismo": 0,
    "camminata": 3.04
  },
  {
    "date": "2025-09-07",
    "corsa": 0,
    "nuoto": 0,
    "ciclismo": 0,
    "camminata": 27.19
  },
  {
    "date": "2025-09-08",
    "corsa": 0,
    "nuoto": 1.8,
    "ciclismo": 0,
    "camminata": 0
  },
  {
    "date": "2025-09-09",
    "corsa": 0,
    "nuoto": 1.88,
    "ciclismo": 0,
    "camminata": 0
  },
  {
    "date": "2025-09-12",
    "corsa": 0,
    "nuoto": 1.95,
    "ciclismo": 0,
    "camminata": 0
  },
  {
    "date": "2025-09-14",
    "corsa": 27.23,
    "nuoto": 0,
    "ciclismo": 0,
    "camminata": 0
  },
  {
    "date": "2025-09-15",
    "corsa": 0,
    "nuoto": 0,
    "ciclismo": 0,
    "camminata": 0
  },
  {
    "date": "2025-09-16",
    "corsa": 0,
    "nuoto": 2.1,
    "ciclismo": 0,
    "camminata": 0
  },
  {
    "date": "2025-09-18",
    "corsa": 0,
    "nuoto": 3.2,
    "ciclismo": 0,
    "camminata": 0
  },
  {
    "date": "2025-09-19",
    "corsa": 0,
    "nuoto": 2.05,
    "ciclismo": 0,
    "camminata": 0
  },
  {
    "date": "2025-09-21",
    "corsa": 4,
    "nuoto": 0,
    "ciclismo": 0,
    "camminata": 3.15
  },
  {
    "date": "2025-09-22",
    "corsa": 0,
    "nuoto": 3.05,
    "ciclismo": 0,
    "camminata": 0
  },
  {
    "date": "2025-09-23",
    "corsa": 0,
    "nuoto": 1.98,
    "ciclismo": 0,
    "camminata": 0
  },
  {
    "date": "2025-09-24",
    "corsa": 0,
    "nuoto": 0,
    "ciclismo": 0,
    "camminata": 0
  },
  {
    "date": "2025-09-25",
    "corsa": 5.07,
    "nuoto": 2.23,
    "ciclismo": 0,
    "camminata": 0
  },
  {
    "date": "2025-09-29",
    "corsa": 0,
    "nuoto": 1.57,
    "ciclismo": 0,
    "camminata": 0
  },
  {
    "date": "2025-09-30",
    "corsa": 0,
    "nuoto": 1.9,
    "ciclismo": 0,
    "camminata": 0
  },
  {
    "date": "2025-10-01",
    "corsa": 0,
    "nuoto": 0,
    "ciclismo": 0,
    "camminata": 3.98
  },
  {
    "date": "2025-10-02",
    "corsa": 0,
    "nuoto": 2.58,
    "ciclismo": 0,
    "camminata": 0
  },
  {
    "date": "2025-10-03",
    "corsa": 0,
    "nuoto": 1.5,
    "ciclismo": 0,
    "camminata": 0
  },
  {
    "date": "2025-10-05",
    "corsa": 7.04,
    "nuoto": 0,
    "ciclismo": 0,
    "camminata": 0
  },
  {
    "date": "2025-10-06",
    "corsa": 0,
    "nuoto": 2.42,
    "ciclismo": 0,
    "camminata": 0
  },
  {
    "date": "2025-10-07",
    "corsa": 0,
    "nuoto": 2,
    "ciclismo": 0,
    "camminata": 0
  },
  {
    "date": "2025-10-08",
    "corsa": 0,
    "nuoto": 0,
    "ciclismo": 0,
    "camminata": 4.07
  },
  {
    "date": "2025-10-09",
    "corsa": 0,
    "nuoto": 2.38,
    "ciclismo": 0,
    "camminata": 0
  },
  {
    "date": "2025-10-10",
    "corsa": 0,
    "nuoto": 2.6,
    "ciclismo": 0,
    "camminata": 0
  },
  {
    "date": "2025-10-11",
    "corsa": 12.76,
    "nuoto": 0,
    "ciclismo": 0,
    "camminata": 0
  },
  {
    "date": "2025-10-13",
    "corsa": 0,
    "nuoto": 2.27,
    "ciclismo": 0,
    "camminata": 0
  },
  {
    "date": "2025-10-14",
    "corsa": 0,
    "nuoto": 3.3,
    "ciclismo": 0,
    "camminata": 0
  },
  {
    "date": "2025-10-15",
    "corsa": 0,
    "nuoto": 0,
    "ciclismo": 0,
    "camminata": 0
  },
  {
    "date": "2025-10-16",
    "corsa": 0,
    "nuoto": 3.55,
    "ciclismo": 0,
    "camminata": 0
  },
  {
    "date": "2025-10-17",
    "corsa": 0,
    "nuoto": 1.52,
    "ciclismo": 0,
    "camminata": 0
  },
  {
    "date": "2025-10-18",
    "corsa": 0,
    "nuoto": 0,
    "ciclismo": 0,
    "camminata": 6.46
  },
  {
    "date": "2025-10-19",
    "corsa": 0,
    "nuoto": 0,
    "ciclismo": 0,
    "camminata": 2.1
  },
  {
    "date": "2025-10-20",
    "corsa": 0,
    "nuoto": 0.88,
    "ciclismo": 0,
    "camminata": 0
  },
  {
    "date": "2025-10-22",
    "corsa": 0,
    "nuoto": 0,
    "ciclismo": 0,
    "camminata": 0
  },
  {
    "date": "2025-10-23",
    "corsa": 0,
    "nuoto": 1.57,
    "ciclismo": 0,
    "camminata": 0
  },
  {
    "date": "2025-10-24",
    "corsa": 0,
    "nuoto": 4.3,
    "ciclismo": 0,
    "camminata": 0
  },
  {
    "date": "2025-10-26",
    "corsa": 0,
    "nuoto": 0,
    "ciclismo": 35.32,
    "camminata": 0
  },
  {
    "date": "2025-10-27",
    "corsa": 0,
    "nuoto": 1.6,
    "ciclismo": 0,
    "camminata": 0
  },
  {
    "date": "2025-10-28",
    "corsa": 0,
    "nuoto": 1.13,
    "ciclismo": 0,
    "camminata": 0
  },
  {
    "date": "2025-10-29",
    "corsa": 0,
    "nuoto": 0,
    "ciclismo": 0,
    "camminata": 0
  },
  {
    "date": "2025-10-30",
    "corsa": 0,
    "nuoto": 0.88,
    "ciclismo": 0,
    "camminata": 0
  },
  {
    "date": "2025-11-01",
    "corsa": 0,
    "nuoto": 0,
    "ciclismo": 0,
    "camminata": 1.63
  },
  {
    "date": "2025-11-03",
    "corsa": 0,
    "nuoto": 1.77,
    "ciclismo": 0,
    "camminata": 0
  },
  {
    "date": "2025-11-04",
    "corsa": 0,
    "nuoto": 1.65,
    "ciclismo": 0,
    "camminata": 0
  },
  {
    "date": "2025-11-05",
    "corsa": 5.17,
    "nuoto": 0,
    "ciclismo": 0,
    "camminata": 0
  },
  {
    "date": "2025-11-06",
    "corsa": 0,
    "nuoto": 1.27,
    "ciclismo": 0,
    "camminata": 0
  },
  {
    "date": "2025-11-07",
    "corsa": 0,
    "nuoto": 1.55,
    "ciclismo": 0,
    "camminata": 0
  },
  {
    "date": "2025-11-09",
    "corsa": 0,
    "nuoto": 0.28,
    "ciclismo": 0,
    "camminata": 0
  },
  {
    "date": "2025-11-10",
    "corsa": 0,
    "nuoto": 0.68,
    "ciclismo": 0,
    "camminata": 0
  },
  {
    "date": "2025-11-11",
    "corsa": 0,
    "nuoto": 1.95,
    "ciclismo": 0,
    "camminata": 0.56
  }
]