[
  {
    "id": 16656096136,
    "date": "2025-12-04",
    "totalMeters": 875,
    "movingSeconds": 4238,
    "pace100m": 484.34285714285716,
    "paceFormatted": "8:04"
  },
  {
    "id": 16632825931,
    "date": "2025-12-02",
    "totalMeters": 800,
    "movingSeconds": 3676,
    "pace100m": 459.5,
    "paceFormatted": "7:40"
  },
  {
    "id": 16623084074,
    "date": "2025-12-01",
    "totalMeters": 1350,
    "movingSeconds": 3727,
    "pace100m": 276.0740740740741,
    "paceFormatted": "4:36"
  },
  {
    "id": 16594687455,
    "date": "2025-11-28",
    "totalMeters": 1625,
    "movingSeconds": 3557,
    "pace100m": 218.89230769230767,
    "paceFormatted": "3:39"
  }
]